[
  {
    "id": "2d0269ab-75b6-48f8-88aa-0f9f6fa4ee87",
    "title": "Remera gráfica de montaña majestuosa",
    "description": "Camiseta negra con diseño de montaña, ideal para los amantes de la naturaleza.",
    "price": 44000,
    "images": "https://i.imgur.com/QkIa5tT.jpeg,https://i.imgur.com/jb5Yu0h.jpeg,https://i.imgur.com/UlxxXyG.jpeg",
    "category_id": "1"
  },
  {
    "id": "87ae06e5-7096-4ce3-af2e-1b6f8623711b",
    "title": "Buzo rojo con capucha",
    "description": "Buzo rojo con capucha y bolsillo canguro, cómoda y casual.",
    "price": 100000,
    "images": "https://i.imgur.com/1twoaDy.jpeg,https://i.imgur.com/FDwQgLy.jpeg,https://i.imgur.com/kg1ZhhH.jpeg",
    "category_id": "1"
  },
  {
    "id": "6895b836-0632-4da4-a961-e579ad7b2612",
    "title": "Buzo gris con capucha",
    "description": "Buzo gris con capucha, ideal para climas frescos.",
    "price": 100000,
    "images": "https://i.imgur.com/cHddUCu.jpeg,https://i.imgur.com/CFOjAgK.jpeg,https://i.imgur.com/wbIMMme.jpeg",
    "category_id": "1"
  },
  {
    "id": "804ec042-9b81-4392-ac3b-76a533912d3a",
    "title": "Buzo gris jaspeado",
    "description": "Buzo gris suave y resistente, perfecta para días relajados.",
    "price": 90000,
    "images": "https://i.imgur.com/R2PN9Wq.jpeg,https://i.imgur.com/IvxMPFr.jpeg,https://i.imgur.com/7eW9nXP.jpeg",
    "category_id": "1"
  },
  {
    "id": "f8d2bcc7-dfaa-4ee2-8f9b-f1250a144a2b",
    "title": "Buzo negro con capucha",
    "description": "Buzo negro cómodo y versátil para cualquier ocasión.",
    "price": 90000,
    "images": "https://i.imgur.com/cSytoSD.jpeg,https://i.imgur.com/WwKucXb.jpeg,https://i.imgur.com/cE2Dxh9.jpeg",
    "category_id": "1"
  },
  {
    "id": "02064888-f93e-44e2-8504-d4dbbab6ce7b",
    "title": "Pantalones deportivos de ajuste cómodo  ",
    "description": "Pantalones deportivos negros cómodos y ligeros, perfectos para cualquier actividad.",
    "price": 250000,
    "images": "https://i.imgur.com/ZKGofuB.jpeg,https://i.imgur.com/GJi73H0.jpeg,https://i.imgur.com/633Fqrz.jpeg",
    "category_id": "1"
  },
  {
    "id": "f6f635a9-61e4-42ca-aba9-634f75560914",
    "title": "Pantalones deportivos con cordón.",
    "description": "Pantalones deportivos cómodos con tela suave y cintura ajustable, ideales para uso diario",
    "price": 290000,
    "images": "https://i.imgur.com/mp3rUty.jpeg,https://i.imgur.com/JQRGIc2.jpeg",
    "category_id": "1"
  },
  {
    "id": "6886dbd4-2818-48b0-b80b-870c131a6cbb",
    "title": "Pantalones deportivos rojos",
    "description": "Pantalones deportivos rojos cómodos con cintura ajustable y bolsillos prácticos.",
    "price": 280000,
    "images": "https://i.imgur.com/9LFjwpI.jpeg,https://i.imgur.com/vzrTgUR.jpeg,https://i.imgur.com/p5NdI6n.jpeg",
    "category_id": "1"
  },
  {
    "id": "2e2b511c-a078-4b9e-b926-277930b107a2",
    "title": "Gorra azul marino",
    "description": "Gorra ajustable azul marino, resistente y versátil para cualquier ocasión.",
    "price": 16000,
    "images": "https://i.imgur.com/R3iobJA.jpeg,https://i.imgur.com/Wv2KTsf.jpeg,https://i.imgur.com/76HAxcA.jpeg",
    "category_id": "1"
  },
  {
    "id": "833014f2-a5ea-4aff-83f5-f9ce393aede5",
    "title": "Gorra azul",
    "description": "Gorra ajustable azul con diseño clásico, cómoda para uso diario.",
    "price": 16000,
    "images": "https://i.imgur.com/wXuQ7bm.jpeg,https://i.imgur.com/BZrIEmb.jpeg,https://i.imgur.com/KcT6BE0.jpeg",
    "category_id": "1"
  },
  {
    "id": "1986db3a-13aa-47fa-bb93-44fed379683f",
    "title": "Gorra roja",
    "description": "Gorra ajustable roja con diseño clásico, cómoda para uso diario.",
    "price": 16000,
    "images": "https://i.imgur.com/cBuLvBi.jpeg,https://i.imgur.com/N1GkCIR.jpeg,https://i.imgur.com/kKc9A5p.jpeg",
    "category_id": "1"
  },
  {
    "id": "8d5a7298-e52a-41cc-b650-c228753857e3",
    "title": "Gorra negra",
    "description": "Gorra ajustable negra con diseño clásico, cómoda para uso diario.",
    "price": 16000,
    "images": "https://i.imgur.com/KeqG6r4.jpeg,https://i.imgur.com/xGQOw3p.jpeg,https://i.imgur.com/oO5OUjb.jpeg",
    "category_id": "1"
  },
  {
    "id": "188f9f7e-b045-444c-9757-2fc1b17fd19c",
    "title": "Shorts verde olivo",
    "description": "Shorts cómodos y versátiles con cintura suave y bolsillos prácticos.",
    "price": 84000,
    "images": "https://i.imgur.com/UsFIvYs.jpeg,https://i.imgur.com/YIq57b6.jpeg",
    "category_id": "1"
  },
  {
    "id": "019d1132-a618-4dcc-8530-02d28ce9d92d",
    "title": "Shorts de cintura alta",
    "description": "Shorts deportivos cómodos con cintura alta y tela transpirable.",
    "price": 43000,
    "images": "https://i.imgur.com/eGOUveI.jpeg,https://i.imgur.com/UcsGO7E.jpeg,https://i.imgur.com/NLn4e7S.jpeg",
    "category_id": "1"
  },
  {
    "id": "4e03f778-5e34-487e-8b99-9d04f74cf2b2",
    "title": "Remera blanca clásica con cuello redondo",
    "description": "Remera básica blanca suave y versátil, ideal para cualquier conjunto.",
    "price": 39000,
    "images": "https://i.imgur.com/axsyGpD.jpeg,https://i.imgur.com/T8oq9X2.jpeg,https://i.imgur.com/J6MinJn.jpeg",
    "category_id": "1"
  },
  {
    "id": "7308c989-8265-4a9a-8d84-39a2c50d3cb8",
    "title": "Remera blanca",
    "description": "Remera blanca cómoda de algodón, perfecta para uso diario.",
    "price": 73000,
    "images": "https://i.imgur.com/Y54Bt8J.jpeg,https://i.imgur.com/SZPDSgy.jpeg,https://i.imgur.com/sJv4Xx0.jpeg",
    "category_id": "1"
  },
  {
    "id": "6413aab0-7e11-4880-af4a-909f163d0f50",
    "title": "Remera negra",
    "description": "Remera negra básica y cómoda, ideal para combinar o usar sola.",
    "price": 73000,
    "images": "https://i.imgur.com/9DqEOV5.jpeg,https://i.imgur.com/ae0AEYn.jpeg,https://i.imgur.com/mZ4rUjj.jpeg",
    "category_id": "1"
  },
  {
    "id": "401c1152-6b78-45d8-801d-dd63bdb2b02f",
    "title": "Control inalámbrico blanco y naranja para juegos",
    "description": "Control ergonómico con diseño moderno, compatible con varias plataformas.",
    "price": 290000,
    "images": "https://i.imgur.com/ZANVnHE.jpeg,https://i.imgur.com/Ro5z6Tn.jpeg,https://i.imgur.com/woA93Li.jpeg",
    "category_id": "2"
  },
  {
    "id": "eb5e9eb4-e819-415f-8165-a16161dc0eda",
    "title": "Auriculares inalámbricos y audífonos",
    "description": "Auriculares y audífonos cómodos y duraderos, perfectos para el día a día.",
    "price": 140000,
    "images": "https://i.imgur.com/yVeIeDa.jpeg,https://i.imgur.com/jByJ4ih.jpeg,https://i.imgur.com/KXj6Tpb.jpeg",
    "category_id": "2"
  },
  {
    "id": "f2114aa6-e428-4fae-a3ae-1deb83c5bd99",
    "title": "Auriculares de diadema cómodos",
    "description": "Auriculares suaves y ajustables con sonido de alta calidad.",
    "price": 280000,
    "images": "https://i.imgur.com/SolkFEB.jpeg,https://i.imgur.com/KIGW49u.jpeg,https://i.imgur.com/mWwek7p.jpeg",
    "category_id": "2"
  },
  {
    "id": "74dbeeb3-7f5a-49a4-be4e-c1d547789ae4",
    "title": "Tostadora eficiente de 2 ranuras",
    "description": "Tostadora compacta con controles ajustables y bandeja extraíble, ideal para cualquier cocina.",
    "price": 148000,
    "images": "https://i.imgur.com/keVCVIa.jpeg,https://i.imgur.com/afHY7v2.jpeg,https://i.imgur.com/yAOihUe.jpeg",
    "category_id": "2"
  },
  {
    "id": "575895da-dca5-42e9-90b1-cc5bb9cc401a",
    "title": "Mouse inalámbrico",
    "description": "Mouse ergonómico inalámbrico con diseño brillante y navegación precisa.",
    "price": 100000,
    "images": "https://i.imgur.com/w3Y8NwQ.jpeg,https://i.imgur.com/WJFOGIC.jpeg,https://i.imgur.com/dV4Nklf.jpeg",
    "category_id": "2"
  },
  {
    "id": "101b3caa-4d87-49ce-80ff-d4eec5f326e8",
    "title": "Portátil moderno con iluminación ambiental",
    "description": "Portátil ultradelgado con pantalla iluminada, ideal para trabajo y entretenimiento.",
    "price": 1430000,
    "images": "https://i.imgur.com/OKn1KFI.jpeg,https://i.imgur.com/G4f21Ai.jpeg,https://i.imgur.com/Z9oKRVJ.jpeg",
    "category_id": "2"
  },
  {
    "id": "5a00abda-d276-4c20-b199-0c7610d7827c",
    "title": "Portátil moderno para profesionales",
    "description": "Portátil ligero y potente, diseñado para profesionales en movimiento.",
    "price": 1970000,
    "images": "https://i.imgur.com/ItHcq7o.jpeg,https://i.imgur.com/55GM3XZ.jpeg,https://i.imgur.com/tcNJxoW.jpeg",
    "category_id": "2"
  },
  {
    "id": "5c29e945-fb4c-44e3-b59d-3dc7c9557a75",
    "title": "Auriculares de diadema rojo y plata",
    "description": " Auriculares cómodos con cable desmontable y sonido de alta calidad.",
    "price": 390000,
    "images": "https://i.imgur.com/YaSqa06.jpeg,https://i.imgur.com/isQAliJ.jpeg,https://i.imgur.com/5B8UQfh.jpeg",
    "category_id": "2"
  },
  {
    "id": "94a1ae4a-7920-4434-9c5f-6d87a3b476c5",
    "title": "Funda para móvil con acabado espejo",
    "description": "Funda reflectante que protege tu móvil con estilo minimalista.",
    "price": 27000,
    "images": "https://i.imgur.com/yb9UQKL.jpeg,https://i.imgur.com/m2owtQG.jpeg,https://i.imgur.com/bNiORct.jpeg",
    "category_id": "2"
  },
  {
    "id": "77b86707-8862-4d94-8a2b-ca0fd5824a9a",
    "title": "Smartwatch moderno con pantalla vibrante",
    "description": "Smartwatch con pantalla táctil y correa cómoda, perfecto para notificaciones y fitness.",
    "price": 160000,
    "images": "https://i.imgur.com/LGk9Jn2.jpeg,https://i.imgur.com/1ttYWaI.jpeg,https://i.imgur.com/sPRWnJH.jpeg",
    "category_id": "2"
  },
  {
    "id": "96a5823a-e9af-43a2-b856-aa39916fb54e",
    "title": "Sofá de cuero",
    "description": "Sofá elegante de cuero con diseño minimalista y patas de metal resistentes.",
    "price": 5300000,
    "images": "https://i.imgur.com/Qphac99.jpeg,https://i.imgur.com/dJjpEgG.jpeg,https://i.imgur.com/MxJyADq.jpeg",
    "category_id": "3"
  },
  {
    "id": "0845a500-0932-4057-915f-3504acfc070b",
    "title": "Mesa de comedor de madera estilo moderno",
    "description": "Mesa elegante con acabado de nogal y patas cónicas, ideal para cualquier decoración.",
    "price": 2400000,
    "images": "https://i.imgur.com/DMQHGA0.jpeg,https://i.imgur.com/qrs9QBg.jpeg,https://i.imgur.com/XVp8T1I.jpeg",
    "category_id": "3"
  },
  {
    "id": "65f6ccbf-845e-4b6a-beb7-eb16f5ff674d",
    "title": "Mesa de comedor con base dorada y superficie de piedra",
    "description": "Mesa lujosa con base dorada y superficie de piedra redonda, perfecta para comidas especiales.",
    "price": 6600000,
    "images": "https://i.imgur.com/NWIJKUj.jpeg,https://i.imgur.com/Jn1YSLk.jpeg,https://i.imgur.com/VNZRvx5.jpeg",
    "category_id": "3"
  },
  {
    "id": "a5e857ab-e92b-4f97-b49f-c00cc051368e",
    "title": "Sillón moderno en color verde azulado",
    "description": "Sillón cómodo con marco de madera y tapizado vibrante, ideal para cualquier espacio.",
    "price": 2500000,
    "images": "https://i.imgur.com/6wkyyIN.jpeg,https://i.imgur.com/Ald3Rec.jpeg,https://i.imgur.com/dIqo03c.jpeg",
    "category_id": "3"
  },
  {
    "id": "a4fdc26a-0c37-46e4-915f-5512566f826c",
    "title": "Mesa de comedor de madera maciza elegante",
    "description": "Mesa contemporánea de madera maciza para hasta seis personas, con diseño minimalista.",
    "price": 6700000,
    "images": "https://i.imgur.com/4lTaHfF.jpeg,https://i.imgur.com/JktHE1C.jpeg,https://i.imgur.com/cQeXQMi.jpeg",
    "category_id": "3"
  },
  {
    "id": "e0f67200-e73e-4a45-b785-2f885e956570",
    "title": "Estación de trabajo minimalista moderna",
    "description": "Escritorio de madera elegante con lámpara ajustable y accesorios, ideal para oficinas en casa.",
    "price": 4900000,
    "images": "https://i.imgur.com/3oXNBst.jpeg,https://i.imgur.com/ErYYZnT.jpeg,https://i.imgur.com/boBPwYW.jpeg",
    "category_id": "3"
  },
  {
    "id": "d350ecea-9e19-49b8-afb3-76391c125a07",
    "title": "Silla de oficina ergonómica",
    "description": "Silla cómoda con altura ajustable y diseño minimalista, perfecta para largas jornadas.",
    "price": 710000,
    "images": "https://i.imgur.com/3dU0m72.jpeg,https://i.imgur.com/zPU3EVa.jpeg",
    "category_id": "3"
  },
  {
    "id": "1496a70d-977c-4d47-b277-20e8813891f2",
    "title": "Botines de fútbol holográficos futuristas",
    "description": "Botines ligeros y llamativos con acabado holográfico, diseñados para destacar.",
    "price": 390000,
    "images": "https://i.imgur.com/qNOjJje.jpeg,https://i.imgur.com/NjfCFnu.jpeg,https://i.imgur.com/eYtvXS1.jpeg",
    "category_id": "4"
  },
  {
    "id": "2a6e5d20-c815-437d-a4df-5cf4a1e330db",
    "title": "Tacones altos con purpurina arcoíris",
    "description": "Tacones brillantes y coloridos, perfectos para destacar en cualquier ocasión especial.",
    "price": 390000,
    "images": "https://i.imgur.com/62gGzeF.jpeg,https://i.imgur.com/5MoPuFM.jpeg,https://i.imgur.com/sUVj7pK.jpeg",
    "category_id": "4"
  },
  {
    "id": "bd049e03-5bce-4c68-95ac-1bf3f4d2c93c",
    "title": "Sandalias de mezclilla para verano",
    "description": "Sandalias de mezclilla con suela de yute y correas ajustables, cómodas y modernas.",
    "price": 330000,
    "images": "https://i.imgur.com/9qrmE1b.jpeg,https://i.imgur.com/wqKxBVH.jpeg,https://i.imgur.com/sWSV6DK.jpeg",
    "category_id": "4"
  },
  {
    "id": "ad50331b-a385-4cd3-a6d8-093a055050b4",
    "title": "Calzado deportivo naranja y azul",
    "description": "Calzado deportivo llamativo con colores naranja y azul, perfecto para estilo y comodidad",
    "price": 270000,
    "images": "https://i.imgur.com/hKcMNJs.jpeg,https://i.imgur.com/NYToymX.jpeg,https://i.imgur.com/HiiapCt.jpeg",
    "category_id": "4"
  },
  {
    "id": "9557c118-3bca-47f5-934f-45c1c35c22d5",
    "title": "Calzado deportivo clásico rosa vibrante",
    "description": "Calzado deportivo rosa con detalles blancos, cómodo y perfecto para el uso diario.",
    "price": 280000,
    "images": "https://i.imgur.com/mcW42Gi.jpeg,https://i.imgur.com/mhn7qsF.jpeg,https://i.imgur.com/F8vhnFJ.jpeg",
    "category_id": "4"
  },
  {
    "id": "4104897d-c988-40bd-9c6a-db6bda699f5e",
    "title": "Calzado deportivo futurista plateado y dorado con plataforma",
    "description": "Calzado deportivo moderno con diseño de caña alta, en colores plateado y dorado.",
    "price": 68,
    "images": "https://i.imgur.com/npLfCGq.jpeg,https://i.imgur.com/vYim3gj.jpeg,https://i.imgur.com/HxuHwBO.jpeg",
    "category_id": "4"
  },
  {
    "id": "8d2f499a-2605-46f5-877e-d8751333eaec",
    "title": "Botines de tacón futuristas",
    "description": "Botines modernos con tacón en bloques de colores y acabado elegante.",
    "price": 360000,
    "images": "https://i.imgur.com/HqYqLnW.jpeg,https://i.imgur.com/RlDGnZw.jpeg,https://i.imgur.com/qa0O6fg.jpeg",
    "category_id": "4"
  },
  {
    "id": "e06c9e4f-4206-4935-8c01-bc1efeb699fd",
    "title": "Zapatos de charol elegantes con tacón dorado",
    "description": "Zapatos abiertos de charol con tacón dorado, ideales para ocasiones formales.",
    "price": 530000,
    "images": "https://i.imgur.com/AzAY4Ed.jpeg,https://i.imgur.com/umfnS9P.jpeg,https://i.imgur.com/uFyuvLg.jpeg",
    "category_id": "4"
  },
  {
    "id": "c63bc844-4ccd-4b87-a348-4a401b45e9e7",
    "title": "Mocasines elegantes de cuero morado",
    "description": "Mocasines morados de cuero, cómodos y con diseño moderno y vibrante.",
    "price": 170000,
    "images": "https://i.imgur.com/Au8J9sX.jpeg,https://i.imgur.com/gdr8BW2.jpeg,https://i.imgur.com/KDCZxnJ.jpeg",
    "category_id": "4"
  },
  {
    "id": "6132ff8d-5892-4345-a7f0-44c64eaabdf5",
    "title": "Zapatos casuales de gamuza azul",
    "description": "Zapatos de gamuza azul con suela de goma, ideales para el uso diario.",
    "price": 190000,
    "images": "https://i.imgur.com/sC0ztOB.jpeg,https://i.imgur.com/Jf9DL9R.jpeg,https://i.imgur.com/R1IN95T.jpeg",
    "category_id": "4"
  },
  {
    "id": "7a8d2238-024c-489b-a0a1-045344645ff8",
    "title": "Bicicleta eléctrica futurista y elegante",
    "description": "Bicicleta eléctrica moderna con diseño único, batería duradera y gran eficiencia.",
    "price": 2200000,
    "images": "https://i.imgur.com/BG8J0Fj.jpg,https://i.imgur.com/ujHBpCX.jpg,https://i.imgur.com/WHeVL9H.jpg",
    "category_id": "5"
  },
  {
    "id": "9cfe32b2-8e85-4a7a-bc7c-c8331914db51",
    "title": "Kart todo terreno",
    "description": "Kart resistente con asiento cómodo y neumáticos robustos, ideal para aventuras.",
    "price": 7300000,
    "images": "https://i.imgur.com/Ex5x3IU.jpg,https://i.imgur.com/z7wAQwe.jpg,https://i.imgur.com/kc0Dj9S.jpg",
    "category_id": "5"
  },
  {
    "id": "a69e845b-063e-4845-b02d-6bd8f74d0893",
    "title": "Perfume cítrico radiante",
    "description": "Fragancia fresca y vibrante con aroma cítrico, perfecta para uso diario.",
    "price": 730000,
    "images": "https://i.imgur.com/xPDwUb3.jpg,https://i.imgur.com/3rfp691.jpg,https://i.imgur.com/kG05a29.jpg",
    "category_id": "5"
  },
  {
    "id": "9cbaffca-3bc3-41ef-a5ac-d262097bb266",
    "title": "Equipaje de mano rígido verde oliva elegante",
    "description": "Maleta compacta y resistente con ruedas suaves y asa telescópica.",
    "price": 480000,
    "images": "https://i.imgur.com/jVfoZnP.jpg,https://i.imgur.com/Tnl15XK.jpg,https://i.imgur.com/7OqTPO6.jpg",
    "category_id": "5"
  },
  {
    "id": "2f0748a1-70c4-4c09-b4cd-e04f2bef1a14",
    "title": "Bolso de mano transparente y moderno",
    "description": "Bolso de acrílico con diseño transparente y detalles dorados, práctico y elegante.",
    "price": 610000,
    "images": "https://i.imgur.com/Lqaqz59.jpg,https://i.imgur.com/uSqWK0m.jpg,https://i.imgur.com/atWACf1.jpg",
    "category_id": "5"
  },
  {
    "id": "d33fbff6-a1e3-4488-9acd-6a91877d4f1d",
    "title": "Gafas de sol con tinte rosa",
    "description": "Gafas de sol con marco negro y cristales rosados, perfectas para destacar con estilo.",
    "price": 83000,
    "images": "https://i.imgur.com/0qQBkxX.jpg,https://i.imgur.com/I5g1DoE.jpg,https://i.imgur.com/myfFQBW.jpg",
    "category_id": "5"
  },
  {
    "id": "a6c6a9e4-50cb-4180-882f-0b9a0217537f",
    "title": "Conjunto elegante de vasos de vidrio",
    "description": "Vasos de vidrio duraderos y modernos, ideales para cualquier bebida o mesa.",
    "price": 150000,
    "images": "https://i.imgur.com/TF0pXdL.jpg,https://i.imgur.com/BLDByXP.jpg,https://i.imgur.com/b7trwCv.jpg",
    "category_id": "5"
  }
]
